minifypy/__init__.py
minifypy/__main__.py
minifypy-0.0.1.dist-info/LICENSE
minifypy-0.0.1.dist-info/WHEEL
minifypy-0.0.1.dist-info/METADATA
minifypy-0.0.1.dist-info/RECORD
