Metadata-Version: 2.1
Name: minifypy
Version: 0.0.1
Summary: minify py file(s)
Author-email: calcuis <info@calcu.io>
Classifier: License :: OSI Approved :: MIT License
Requires-Dist: pyminify
Project-URL: GitHub, https://github.com/calcuis/minifypy
Project-URL: Issues, https://github.com/calcuis/minifypy/issues
